setup.py
zfx_multiproc/__init__.py
zfx_multiproc/多进程_创建进程锁.py
zfx_multiproc/多进程_启动进程.py
zfx_multiproc/多进程_等待进程运行结束_列表.py
zfx_multiproc/多进程_进程对象_取PID.py
zfx_multiproc/多进程_进程对象_取名称.py
zfx_multiproc/多进程_进程对象_取退出代码.py
zfx_multiproc/多进程_进程对象_检查是否运行.py
zfx_multiproc/多进程_进程对象_等待结束.py
zfx_multiproc/多进程_进程对象_终止进程.py
zfx_multiproc/多进程_队列_创建.py
zfx_multiproc/多进程_队列_取出.py
zfx_multiproc/多进程_队列_放入.py
zfx_multiproc/多进程_队列_是否满.py
zfx_multiproc/多进程_队列_是否空.py
zfx_multiproc.egg-info/PKG-INFO
zfx_multiproc.egg-info/SOURCES.txt
zfx_multiproc.egg-info/dependency_links.txt
zfx_multiproc.egg-info/top_level.txt